dirimport/__init__.py
dirimport/_cli.py
dirimport/_version.py
dirimport/gen.py
dirimport-0.0.6.dist-info/LICENSE
dirimport-0.0.6.dist-info/METADATA
dirimport-0.0.6.dist-info/WHEEL
dirimport-0.0.6.dist-info/entry_points.txt
dirimport-0.0.6.dist-info/top_level.txt
dirimport-0.0.6.dist-info/RECORD
