Metadata-Version: 2.1
Name: dirimport
Version: 0.0.6
Summary: import your library without __init__.py
Home-page: https://github.com/wtnb75/dirimport
Author: Watanabe Takashi
Author-email: wtnb75@gmail.com
License: MIT
Platform: UNKNOWN
Classifier: Development Status :: 3 - Alpha
Classifier: Intended Audience :: Developers
Classifier: License :: OSI Approved :: MIT License
Classifier: Topic :: Software Development :: Libraries :: Python Modules
Classifier: Programming Language :: Python :: 3
Requires-Dist: Jinja2
Requires-Dist: Click
